{
  "$schema": "https://github.com/Lordfirespeed/ConfiguredYoutubeBoombox/raw/main/assets/configured-youtube-boombox-tracks.schema.json",
  "tracks": [
    {
      "youtubeVideoId": "OdS8Hj4zNaw",
      "trackName": "portal-radio"
    },
    {
      "youtubeVideoId": "A5wBk9946Ew",
      "trackName": "astronomia",
      "startTimestamp": "00:00:18.00",
      "endTimestamp": "00:01:14.00",
      "volumeScalar": 0.25
    },
    {
      "youtubeVideoId": "PxTgPNWeBZk",
      "trackName": "skeletor-feliz-navidad"
    },
    {
      "youtubeVideoId": "-ol3PSROlwg",
      "trackName": "all-my-fellas"
    },
    {
      "youtubeVideoId": "MK6TXMsvgQg",
      "trackName": "benny-hill"
    },
    {
      "youtubeVideoId": "L_jWHffIx5E",
      "trackName": "all-star",
      "startTimestamp": "00:00:36.50",
      "volumeScalar": 0.4
    }
  ]
}
